hysp/__init__.py
hysp/greet.py
hysp-0.0.1.dist-info/METADATA
hysp-0.0.1.dist-info/WHEEL
hysp-0.0.1.dist-info/top_level.txt
hysp-0.0.1.dist-info/RECORD
