Metadata-Version: 2.1
Name: hysp
Version: 0.0.1
Summary: A package template
Home-page: https://github.com/yourusername/hysp
Author: Your Name
Author-email: your.email@example.com
License: UNKNOWN
Platform: UNKNOWN
Classifier: Programming Language :: Python :: 3
Classifier: License :: OSI Approved :: MIT License
Classifier: Operating System :: OS Independent
Requires-Python: >=3.9
